ocrguru/cli.py
ocrguru/core.py
ocrguru-0.1.0.dist-info/licenses/LICENSE
ocrguru-0.1.0.dist-info/METADATA
ocrguru-0.1.0.dist-info/WHEEL
ocrguru-0.1.0.dist-info/entry_points.txt
ocrguru-0.1.0.dist-info/top_level.txt
ocrguru-0.1.0.dist-info/RECORD
