Metadata-Version: 2.4
Name: ocrguru
Version: 0.1.0
Summary: CLI wrapper for Docling OCR engines
Requires-Python: >=3.8
License-File: LICENSE
Requires-Dist: docling>=0.9.0
Requires-Dist: PyPDF2
Requires-Dist: huggingface-hub
Dynamic: license-file
